{
	"tiket": [
		{
			"id": 1,
			"user_id": 1,
			"penumpang_id": 1,
			"kereta_id": 1
		},
		{
			"id": 2,
			"user_id": 1,
			"penumpang_id": 2,
			"kereta_id": 1
		},
		{
			"id": 3,
			"user_id": 2,
			"penumpang_id": 1,
			"kereta_id": 3
		}
	], 
	"user": [
		{
			"id": 1,
			"username": "akmalkomeng",
			"nama": "Akmal Abhirama",
			"verified": true,
			"email": "akmalabhirama@gmail.com",
			"password": "akmal321"
		},
		{
			"id": 2,
			"username": "tatanxsudiro",
			"nama": "Tatang Sudiarto",
			"verified": false,
			"email": "tatanx@gmail.com",
			"password": "tatanxgtg"
		},
		{
			"id": 3,
			"username": "akulapar",
			"nama": "Sumanto",
			"verified": true,
			"email": "Sumanto@gmail.com",
			"password": "sumantolapar"
		},
		{
			"id": 4,
			"username": "botaklucu",
			"nama": "Deddy Cagur",
			"verified": true,
			"email": "Cagurgur@gmail.com",
			"password": "sayatidakbotak"
		}
	],
	"kereta": [
		{
			"id": 1,
			"merk": "Argo Wilis",
			"tipe": "Antar Kota",
			"jml_gerbong": 13
		},
		{
			"id": 2,
			"merk": "Kutojaya",
			"tipe": "Lokal",
			"jml_gerbong": 9
		},
		{
			"id": 3,
			"merk": "Thomas",
			"tipe": "Antar Kota",
			"jml_gerbong":18
		}
	]
}
